myproject/__init__.py
myproject/main.py
myproject/sample.py
uvexample-1.0.2.dist-info/METADATA
uvexample-1.0.2.dist-info/WHEEL
uvexample-1.0.2.dist-info/top_level.txt
uvexample-1.0.2.dist-info/RECORD
