Metadata-Version: 2.4
Name: uvexample
Version: 1.0.2
Summary: Add your description here
Requires-Python: >=3.9
Requires-Dist: pytest>=8.4.2
Requires-Dist: ruff>=0.13.2
